sgqlc/__init__.py
sgqlc/codegen/__init__.py
sgqlc/codegen/__main__.py
sgqlc/codegen/operation.py
sgqlc/codegen/schema.py
sgqlc/endpoint/__init__.py
sgqlc/endpoint/base.py
sgqlc/endpoint/http.py
sgqlc/endpoint/httpx.py
sgqlc/endpoint/requests.py
sgqlc/endpoint/websocket.py
sgqlc/introspection/__init__.py
sgqlc/introspection/__main__.py
sgqlc/operation/__init__.py
sgqlc/types/__init__.py
sgqlc/types/datetime.py
sgqlc/types/relay.py
sgqlc/types/uuid.py
sgqlc-17.dist-info/AUTHORS
sgqlc-17.dist-info/LICENSE
sgqlc-17.dist-info/METADATA
sgqlc-17.dist-info/WHEEL
sgqlc-17.dist-info/entry_points.txt
sgqlc-17.dist-info/RECORD
