Metadata-Version: 2.3
Name: sgqlc
Version: 17
Summary: Simple GraphQL Client
License: ISCL
Keywords: graphql,client,http,endpoint
Author: Gustavo Sverzut Barbieri
Author-email: barbieri@profusion.mobi
Requires-Python: >=3.8,<4
Classifier: Development Status :: 4 - Beta
Classifier: Environment :: Console
Classifier: Environment :: Web Environment
Classifier: Intended Audience :: Developers
Classifier: License :: OSI Approved :: ISC License (ISCL)
Classifier: Operating System :: OS Independent
Classifier: Programming Language :: Python
Classifier: Topic :: Utilities
Provides-Extra: httpx
Provides-Extra: requests
Provides-Extra: websocket
Requires-Dist: graphql-core (>=3.2.6,<3.3.0)
Requires-Dist: httpx ; extra == "httpx"
Requires-Dist: requests ; extra == "requests"
Requires-Dist: websocket-client ; extra == "websocket"
Project-URL: Documentation, https://sgqlc.readthedocs.io/
Project-URL: Homepage, http://github.com/profusion/sgqlc
Project-URL: Repository, http://github.com/profusion/sgqlc
